[
    {
        "href": "http://d.duotuwang.com/2021/02/05/23963/",
        "name": "[UGirlsAPP]\u7231\u5c24\u7269 No.2016 \u4e0e\u4f17\u8c03\u60c5",
        "count": 35,
        "src": "http://d.duotuwang.com/2021/02/05/23963/0.jpg"
    },
    {
        "href": "http://d.duotuwang.com/2020/04/02/20158/",
        "name": "[MyGirl]\u7f8e\u5a9b\u9986 VOL.434 \u4efb\u83b9\u6a31",
        "count": 53,
        "src": "http://d.duotuwang.com/2020/04/02/20158/0.jpg"
    },
    {
        "href": "http://d.duotuwang.com/2020/03/23/20013/",
        "name": "[XIUREN]\u79c0\u4eba\u7f51 No.2088 \u4efb\u83b9\u6a31",
        "count": 40,
        "src": "http://d.duotuwang.com/2020/03/23/20013/0.jpg"
    },
    {
        "href": "http://d.duotuwang.com/2020/02/21/19684/",
        "name": "[XIUREN]\u79c0\u4eba\u7f51 No.1994 \u4efb\u83b9\u6a31",
        "count": 40,
        "src": "http://d.duotuwang.com/2020/02/21/19684/0.jpg"
    },
    {
        "href": "http://d.duotuwang.com/2019/11/14/18575/",
        "name": "[XIUREN]\u79c0\u4eba\u7f51 No.1790 \u4efb\u83b9\u6a31",
        "count": 40,
        "src": "http://d.duotuwang.com/2019/11/14/18575/0.jpg"
    },
    {
        "href": "http://d.duotuwang.com/2019/09/09/17907/",
        "name": "[XIUREN]\u79c0\u4eba\u7f51 No.1672 \u4efb\u83b9\u6a31",
        "count": 30,
        "src": "http://d.duotuwang.com/2019/09/09/17907/0.jpg"
    },
    {
        "href": "http://d.duotuwang.com/2019/08/15/17688/",
        "name": "[XIUREN]\u79c0\u4eba\u7f51 No.1621 \u4efb\u83b9\u6a31",
        "count": 40,
        "src": "http://d.duotuwang.com/2019/08/15/17688/0.jpg"
    },
    {
        "href": "http://d.duotuwang.com/2019/07/22/17237/",
        "name": "[MyGirl]\u7f8e\u5a9b\u9986 VOL.372 \u4efb\u83b9\u6a31",
        "count": 64,
        "src": "http://d.duotuwang.com/2019/07/22/17237/0.jpg"
    },
    {
        "href": "http://d.duotuwang.com/2019/06/17/16846/",
        "name": "[XIUREN]\u79c0\u4eba\u7f51 No.1500 \u4efb\u83b9\u6a31Jenny",
        "count": 39,
        "src": "http://d.duotuwang.com/2019/06/17/16846/0.jpg"
    },
    {
        "href": "http://d.duotuwang.com/2019/05/17/16494/",
        "name": "[XIUREN]\u79c0\u4eba\u7f51 No.1457 \u4efb\u83b9\u6a31Jenny",
        "count": 45,
        "src": "http://d.duotuwang.com/2019/05/17/16494/0.jpg"
    },
    {
        "href": "http://d.duotuwang.com/2019/05/15/16505/",
        "name": "[MFStar]\u6a21\u8303\u5b66\u9662 VOL.191 \u4efb\u83b9\u6a31Jenny",
        "count": 41,
        "src": "http://d.duotuwang.com/2019/05/15/16505/0.jpg"
    },
    {
        "href": "http://d.duotuwang.com/2019/04/11/16027/",
        "name": "[MFStar]\u6a21\u8303\u5b66\u9662 VOL.184 Jennanni_Jen",
        "count": 45,
        "src": "http://d.duotuwang.com/2019/04/11/16027/0.jpg"
    },
    {
        "href": "http://d.duotuwang.com/2018/12/17/10130/",
        "name": "[UGirlsAPP]\u7231\u5c24\u7269 No.1307 Jennanni_Jen \u7231\u7684\u91cd\u91cf",
        "count": 35,
        "src": "http://d.duotuwang.com/2018/12/17/10130/0.jpg"
    },
    {
        "href": "http://d.duotuwang.com/2018/12/03/10079/",
        "name": "[MFStar]\u6a21\u8303\u5b66\u9662 VOL.166 Jennanni_Jen",
        "count": 33,
        "src": "http://d.duotuwang.com/2018/12/03/10079/0.jpg"
    },
    {
        "href": "http://d.duotuwang.com/2018/05/30/8916/",
        "name": "[MFStar]\u6a21\u8303\u5b66\u9662 VOL.124 Jennanni_Jen",
        "count": 45,
        "src": "http://d.duotuwang.com/2018/05/30/8916/0.jpg"
    },
    {
        "href": "http://d.duotuwang.com/2018/05/28/8874/",
        "name": "[FEILIN]\u55f2\u56e1\u56e1 VOL.141 Jennanni_Jen",
        "count": 31,
        "src": "http://d.duotuwang.com/2018/05/28/8874/0.jpg"
    },
    {
        "href": "http://d.duotuwang.com/2018/03/14/8445/",
        "name": "[FEILIN]\u55f2\u56e1\u56e1 VOL.127 Jennanni_Jen",
        "count": 38,
        "src": "http://d.duotuwang.com/2018/03/14/8445/0.jpg"
    }
]