[
    {
        "href": "http://d.duotuwang.com/2020/03/24/20004/",
        "name": "[MiStar]\u9b45\u598d\u793e VOL.322 nova\u674e\u96c5",
        "count": 41,
        "src": "http://d.duotuwang.com/2020/03/24/20004/0.jpg"
    },
    {
        "href": "http://d.duotuwang.com/2020/03/02/19739/",
        "name": "[YouWu]\u5c24\u7269\u9986 VOL.170 nova\u674e\u96c5",
        "count": 52,
        "src": "http://d.duotuwang.com/2020/03/02/19739/0.jpg"
    },
    {
        "href": "http://d.duotuwang.com/2020/02/14/19583/",
        "name": "[XIAOYU]\u8bed\u753b\u754c VOL.246 nova\u674e\u96c5",
        "count": 81,
        "src": "http://d.duotuwang.com/2020/02/14/19583/0.jpg"
    },
    {
        "href": "http://d.duotuwang.com/2019/12/05/18802/",
        "name": "[YouWu]\u5c24\u7269\u9986 VOL.166 nova\u674e\u96c5",
        "count": 52,
        "src": "http://d.duotuwang.com/2019/12/05/18802/0.jpg"
    },
    {
        "href": "http://d.duotuwang.com/2019/12/03/18776/",
        "name": "[IMISS]\u7231\u871c\u793e VOL.409 nova\u674e\u96c5",
        "count": 52,
        "src": "http://d.duotuwang.com/2019/12/03/18776/0.jpg"
    },
    {
        "href": "http://d.duotuwang.com/2019/11/25/18706/",
        "name": "[MyGirl]\u7f8e\u5a9b\u9986 VOL.410 nova\u674e\u96c5",
        "count": 58,
        "src": "http://d.duotuwang.com/2019/11/25/18706/0.jpg"
    },
    {
        "href": "http://d.duotuwang.com/2019/11/20/18658/",
        "name": "[IMISS]\u7231\u871c\u793e VOL.402 nova\u674e\u96c5",
        "count": 44,
        "src": "http://d.duotuwang.com/2019/11/20/18658/0.jpg"
    },
    {
        "href": "http://d.duotuwang.com/2019/11/05/18480/",
        "name": "[YouWu]\u5c24\u7269\u9986 VOL.163 nova\u674e\u96c5",
        "count": 53,
        "src": "http://d.duotuwang.com/2019/11/05/18480/0.jpg"
    },
    {
        "href": "http://d.duotuwang.com/2019/10/28/18406/",
        "name": "[XIAOYU]\u8bed\u753b\u754c VOL.180 nova\u674e\u96c5",
        "count": 91,
        "src": "http://d.duotuwang.com/2019/10/28/18406/0.jpg"
    },
    {
        "href": "http://d.duotuwang.com/2019/10/24/18339/",
        "name": "[IMISS]\u7231\u871c\u793e VOL.389 nova\u674e\u96c5",
        "count": 51,
        "src": "http://d.duotuwang.com/2019/10/24/18339/0.jpg"
    },
    {
        "href": "http://d.duotuwang.com/2019/10/09/18215/",
        "name": "[XIAOYU]\u8bed\u753b\u754c VOL.166 nova\u674e\u96c5",
        "count": 72,
        "src": "http://d.duotuwang.com/2019/10/09/18215/0.jpg"
    },
    {
        "href": "http://d.duotuwang.com/2019/09/29/18148/",
        "name": "[IMISS]\u7231\u871c\u793e 2019.09.29 VOL.378 nova\u674e\u96c5",
        "count": 39,
        "src": "http://d.duotuwang.com/2019/09/29/18148/0.jpg"
    },
    {
        "href": "http://d.duotuwang.com/2019/09/06/17861/",
        "name": "[MiStar]\u9b45\u598d\u793e VOL.305 nova\u674e\u96c5",
        "count": 42,
        "src": "http://d.duotuwang.com/2019/09/06/17861/0.jpg"
    },
    {
        "href": "http://d.duotuwang.com/2019/07/17/17211/",
        "name": "[MiStar]\u9b45\u598d\u793e VOL.298 Abby\u674e\u96c5",
        "count": 42,
        "src": "http://d.duotuwang.com/2019/07/17/17211/0.jpg"
    },
    {
        "href": "http://d.duotuwang.com/2019/07/01/16966/",
        "name": "[MiStar]\u9b45\u598d\u793e VOL.296 Abby\u674e\u96c5",
        "count": 31,
        "src": "http://d.duotuwang.com/2019/07/01/16966/0.jpg"
    },
    {
        "href": "http://d.duotuwang.com/2019/06/12/16816/",
        "name": "[MiStar]\u9b45\u598d\u793e VOL.294 Abby\u674e\u96c5",
        "count": 31,
        "src": "http://d.duotuwang.com/2019/06/12/16816/0.jpg"
    },
    {
        "href": "http://d.duotuwang.com/2018/08/21/9528/",
        "name": "[HuaYang]\u82b1\u6f3eshow VOL.073 Abby\u674e\u96c5",
        "count": 40,
        "src": "http://d.duotuwang.com/2018/08/21/9528/0.jpg"
    },
    {
        "href": "http://d.duotuwang.com/2018/04/11/8605/",
        "name": "[HuaYang]\u82b1\u6f3eshow VOL.040 Abby\u674e\u96c5",
        "count": 41,
        "src": "http://d.duotuwang.com/2018/04/11/8605/0.jpg"
    },
    {
        "href": "http://d.duotuwang.com/2017/12/29/6723/",
        "name": "[HuaYang]\u82b1\u6f3eshow VOL.021 Abby\u674e\u96c5",
        "count": 42,
        "src": "http://d.duotuwang.com/2017/12/29/6723/0.jpg"
    },
    {
        "href": "http://d.duotuwang.com/2017/03/21/3661/",
        "name": "[IMISS]\u7231\u871c\u793e VOL.156 Abby\u674e\u96c5",
        "count": 36,
        "src": "http://d.duotuwang.com/2017/03/21/3661/0.jpg"
    },
    {
        "href": "http://d.duotuwang.com/2017/02/10/2075/",
        "name": "[IMISS]\u7231\u871c\u793e VOL.151 Abby\u674e\u96c5",
        "count": 47,
        "src": "http://d.duotuwang.com/2017/02/10/2075/0.jpg"
    },
    {
        "href": "http://d.duotuwang.com/2017/01/19/2038/",
        "name": "[HuaYan]\u82b1\u306e\u989c VOL.022 Abby\u674e\u96c5",
        "count": 50,
        "src": "http://d.duotuwang.com/2017/01/19/2038/0.jpg"
    },
    {
        "href": "http://d.duotuwang.com/2016/12/29/1979/",
        "name": "[MiStar]\u9b45\u598d\u793e VOL.144 Abby\u674e\u96c5",
        "count": 45,
        "src": "http://d.duotuwang.com/2016/12/29/1979/0.jpg"
    }
]