[
    {
        "href": "http://d.duotuwang.com/2017/02/18/4165/",
        "name": "[MF]\u840c\u7f1a MF003 \u54c8\u59aeHAANI",
        "count": 40,
        "src": "http://d.duotuwang.com/2017/02/18/4165/0.jpg"
    },
    {
        "href": "http://d.duotuwang.com/2017/02/06/4164/",
        "name": "[MF]\u840c\u7f1a MF002 \u590f\u5c0f\u79cb\u79cb\u79cb",
        "count": 40,
        "src": "http://d.duotuwang.com/2017/02/06/4164/0.jpg"
    },
    {
        "href": "http://d.duotuwang.com/2016/08/15/4163/",
        "name": "[MF]\u840c\u7f1a MF001 \u7cef\u7c73\u751c\u5b9d\u5b9d",
        "count": 54,
        "src": "http://d.duotuwang.com/2016/08/15/4163/0.jpg"
    }
]