[
    {
        "href": "http://d.duotuwang.com/2021/03/15/24420/",
        "name": "[ROSI\u5199\u771f]\u53e3\u7f69\u7cfb\u5217 KZ.1737",
        "count": 53,
        "src": "http://d.duotuwang.com/2021/03/15/24420/0.jpg"
    },
    {
        "href": "http://d.duotuwang.com/2021/03/14/24419/",
        "name": "[ROSI\u5199\u771f]\u53e3\u7f69\u7cfb\u5217 KZ.1736",
        "count": 44,
        "src": "http://d.duotuwang.com/2021/03/14/24419/0.jpg"
    },
    {
        "href": "http://d.duotuwang.com/2021/03/13/24418/",
        "name": "[ROSI\u5199\u771f]\u53e3\u7f69\u7cfb\u5217 KZ.1735",
        "count": 51,
        "src": "http://d.duotuwang.com/2021/03/13/24418/0.jpg"
    },
    {
        "href": "http://d.duotuwang.com/2021/03/12/24417/",
        "name": "[ROSI\u5199\u771f]\u53e3\u7f69\u7cfb\u5217 KZ.1734",
        "count": 27,
        "src": "http://d.duotuwang.com/2021/03/12/24417/0.jpg"
    },
    {
        "href": "http://d.duotuwang.com/2021/03/11/24416/",
        "name": "[ROSI\u5199\u771f]\u53e3\u7f69\u7cfb\u5217 KZ.1733",
        "count": 45,
        "src": "http://d.duotuwang.com/2021/03/11/24416/0.jpg"
    },
    {
        "href": "http://d.duotuwang.com/2021/03/10/24415/",
        "name": "[ROSI\u5199\u771f]\u53e3\u7f69\u7cfb\u5217 KZ.1732",
        "count": 37,
        "src": "http://d.duotuwang.com/2021/03/10/24415/0.jpg"
    },
    {
        "href": "http://d.duotuwang.com/2021/03/09/24414/",
        "name": "[ROSI\u5199\u771f]\u53e3\u7f69\u7cfb\u5217 KZ.1731",
        "count": 32,
        "src": "http://d.duotuwang.com/2021/03/09/24414/0.jpg"
    },
    {
        "href": "http://d.duotuwang.com/2021/03/08/24413/",
        "name": "[ROSI\u5199\u771f]\u53e3\u7f69\u7cfb\u5217 KZ.1730",
        "count": 44,
        "src": "http://d.duotuwang.com/2021/03/08/24413/0.jpg"
    },
    {
        "href": "http://d.duotuwang.com/2021/03/07/24412/",
        "name": "[ROSI\u5199\u771f]\u53e3\u7f69\u7cfb\u5217 KZ.1729",
        "count": 35,
        "src": "http://d.duotuwang.com/2021/03/07/24412/0.jpg"
    },
    {
        "href": "http://d.duotuwang.com/2021/03/06/24411/",
        "name": "[ROSI\u5199\u771f]\u53e3\u7f69\u7cfb\u5217 KZ.1728",
        "count": 50,
        "src": "http://d.duotuwang.com/2021/03/06/24411/0.jpg"
    },
    {
        "href": "http://d.duotuwang.com/2021/03/05/24410/",
        "name": "[ROSI\u5199\u771f]\u53e3\u7f69\u7cfb\u5217 KZ.1727",
        "count": 98,
        "src": "http://d.duotuwang.com/2021/03/05/24410/0.jpg"
    },
    {
        "href": "http://d.duotuwang.com/2021/03/04/24409/",
        "name": "[ROSI\u5199\u771f]\u53e3\u7f69\u7cfb\u5217 KZ.1726",
        "count": 28,
        "src": "http://d.duotuwang.com/2021/03/04/24409/0.jpg"
    },
    {
        "href": "http://d.duotuwang.com/2021/03/03/24408/",
        "name": "[ROSI\u5199\u771f]\u53e3\u7f69\u7cfb\u5217 KZ.1725",
        "count": 52,
        "src": "http://d.duotuwang.com/2021/03/03/24408/0.jpg"
    },
    {
        "href": "http://d.duotuwang.com/2021/03/02/24407/",
        "name": "[ROSI\u5199\u771f]\u53e3\u7f69\u7cfb\u5217 KZ.1724",
        "count": 19,
        "src": "http://d.duotuwang.com/2021/03/02/24407/0.jpg"
    },
    {
        "href": "http://d.duotuwang.com/2021/03/01/24188/",
        "name": "[ROSI\u5199\u771f]\u53e3\u7f69\u7cfb\u5217 KZ.1723",
        "count": 85,
        "src": "http://d.duotuwang.com/2021/03/01/24188/0.jpg"
    },
    {
        "href": "http://d.duotuwang.com/2021/02/28/24187/",
        "name": "[ROSI\u5199\u771f]\u53e3\u7f69\u7cfb\u5217 KZ.1722",
        "count": 52,
        "src": "http://d.duotuwang.com/2021/02/28/24187/0.jpg"
    },
    {
        "href": "http://d.duotuwang.com/2021/02/27/24186/",
        "name": "[ROSI\u5199\u771f]\u53e3\u7f69\u7cfb\u5217 KZ.1721",
        "count": 59,
        "src": "http://d.duotuwang.com/2021/02/27/24186/0.jpg"
    },
    {
        "href": "http://d.duotuwang.com/2021/02/26/24371/",
        "name": "[ROSI\u5199\u771f]\u53e3\u7f69\u7cfb\u5217 KZ.1720 2/2",
        "count": 51,
        "src": "http://d.duotuwang.com/2021/02/26/24371/0.jpg"
    },
    {
        "href": "http://d.duotuwang.com/2021/02/26/24185/",
        "name": "[ROSI\u5199\u771f]\u53e3\u7f69\u7cfb\u5217 KZ.1720 1/2",
        "count": 52,
        "src": "http://d.duotuwang.com/2021/02/26/24185/0.jpg"
    },
    {
        "href": "http://d.duotuwang.com/2021/02/25/24184/",
        "name": "[ROSI\u5199\u771f]\u53e3\u7f69\u7cfb\u5217 KZ.1719",
        "count": 85,
        "src": "http://d.duotuwang.com/2021/02/25/24184/0.jpg"
    },
    {
        "href": "http://d.duotuwang.com/2021/02/24/24370/",
        "name": "[ROSI\u5199\u771f]\u53e3\u7f69\u7cfb\u5217 KZ.1718 2/2",
        "count": 80,
        "src": "http://d.duotuwang.com/2021/02/24/24370/0.jpg"
    },
    {
        "href": "http://d.duotuwang.com/2021/02/24/24183/",
        "name": "[ROSI\u5199\u771f]\u53e3\u7f69\u7cfb\u5217 KZ.1718 1/2",
        "count": 82,
        "src": "http://d.duotuwang.com/2021/02/24/24183/0.jpg"
    },
    {
        "href": "http://d.duotuwang.com/2021/02/22/24181/",
        "name": "[ROSI\u5199\u771f]\u53e3\u7f69\u7cfb\u5217 KZ.1716",
        "count": 58,
        "src": "http://d.duotuwang.com/2021/02/22/24181/0.jpg"
    },
    {
        "href": "http://d.duotuwang.com/2021/02/21/24180/",
        "name": "[ROSI\u5199\u771f]\u53e3\u7f69\u7cfb\u5217 KZ.1715",
        "count": 43,
        "src": "http://d.duotuwang.com/2021/02/21/24180/0.jpg"
    },
    {
        "href": "http://d.duotuwang.com/2021/02/20/24369/",
        "name": "[ROSI\u5199\u771f]\u53e3\u7f69\u7cfb\u5217 KZ.1714 2/2",
        "count": 75,
        "src": "http://d.duotuwang.com/2021/02/20/24369/0.jpg"
    },
    {
        "href": "http://d.duotuwang.com/2021/02/20/24179/",
        "name": "[ROSI\u5199\u771f]\u53e3\u7f69\u7cfb\u5217 KZ.1714 1/2",
        "count": 78,
        "src": "http://d.duotuwang.com/2021/02/20/24179/0.jpg"
    },
    {
        "href": "http://d.duotuwang.com/2021/02/19/24178/",
        "name": "[ROSI\u5199\u771f]\u53e3\u7f69\u7cfb\u5217 KZ.1713",
        "count": 53,
        "src": "http://d.duotuwang.com/2021/02/19/24178/0.jpg"
    },
    {
        "href": "http://d.duotuwang.com/2021/02/18/24177/",
        "name": "[ROSI\u5199\u771f]\u53e3\u7f69\u7cfb\u5217 KZ.1712",
        "count": 65,
        "src": "http://d.duotuwang.com/2021/02/18/24177/0.jpg"
    },
    {
        "href": "http://d.duotuwang.com/2021/02/17/24176/",
        "name": "[ROSI\u5199\u771f]\u53e3\u7f69\u7cfb\u5217 KZ.1711",
        "count": 94,
        "src": "http://d.duotuwang.com/2021/02/17/24176/0.jpg"
    },
    {
        "href": "http://d.duotuwang.com/2021/02/16/24175/",
        "name": "[ROSI\u5199\u771f]\u53e3\u7f69\u7cfb\u5217 KZ.1710",
        "count": 61,
        "src": "http://d.duotuwang.com/2021/02/16/24175/0.jpg"
    }
]