[
    {
        "href": "http://d.duotuwang.com/2019/03/28/14731/",
        "name": "[ROSI\u5199\u771f]\u53e3\u7f69\u7cfb\u5217 KZ.1019",
        "count": 73,
        "src": "http://d.duotuwang.com/2019/03/28/14731/0.jpg"
    },
    {
        "href": "http://d.duotuwang.com/2019/03/27/14698/",
        "name": "[ROSI\u5199\u771f]\u53e3\u7f69\u7cfb\u5217 KZ.1018",
        "count": 76,
        "src": "http://d.duotuwang.com/2019/03/27/14698/0.jpg"
    },
    {
        "href": "http://d.duotuwang.com/2019/03/26/14699/",
        "name": "[ROSI\u5199\u771f]\u53e3\u7f69\u7cfb\u5217 KZ.1017",
        "count": 68,
        "src": "http://d.duotuwang.com/2019/03/26/14699/0.jpg"
    },
    {
        "href": "http://d.duotuwang.com/2019/03/25/14700/",
        "name": "[ROSI\u5199\u771f]\u53e3\u7f69\u7cfb\u5217 KZ.1016",
        "count": 44,
        "src": "http://d.duotuwang.com/2019/03/25/14700/0.jpg"
    },
    {
        "href": "http://d.duotuwang.com/2019/03/24/14612/",
        "name": "[ROSI\u5199\u771f]\u53e3\u7f69\u7cfb\u5217 KZ.1015",
        "count": 51,
        "src": "http://d.duotuwang.com/2019/03/24/14612/0.jpg"
    },
    {
        "href": "http://d.duotuwang.com/2019/03/23/14613/",
        "name": "[ROSI\u5199\u771f]\u53e3\u7f69\u7cfb\u5217 KZ.1014",
        "count": 61,
        "src": "http://d.duotuwang.com/2019/03/23/14613/0.jpg"
    },
    {
        "href": "http://d.duotuwang.com/2019/03/22/14614/",
        "name": "[ROSI\u5199\u771f]\u53e3\u7f69\u7cfb\u5217 KZ.1013",
        "count": 33,
        "src": "http://d.duotuwang.com/2019/03/22/14614/0.jpg"
    },
    {
        "href": "http://d.duotuwang.com/2019/03/21/14615/",
        "name": "[ROSI\u5199\u771f]\u53e3\u7f69\u7cfb\u5217 KZ.1012",
        "count": 56,
        "src": "http://d.duotuwang.com/2019/03/21/14615/0.jpg"
    },
    {
        "href": "http://d.duotuwang.com/2019/03/20/14616/",
        "name": "[ROSI\u5199\u771f]\u53e3\u7f69\u7cfb\u5217 KZ.1011",
        "count": 56,
        "src": "http://d.duotuwang.com/2019/03/20/14616/0.jpg"
    },
    {
        "href": "http://d.duotuwang.com/2019/03/19/14617/",
        "name": "[ROSI\u5199\u771f]\u53e3\u7f69\u7cfb\u5217 KZ.1010",
        "count": 78,
        "src": "http://d.duotuwang.com/2019/03/19/14617/0.jpg"
    },
    {
        "href": "http://d.duotuwang.com/2019/03/18/14618/",
        "name": "[ROSI\u5199\u771f]\u53e3\u7f69\u7cfb\u5217 KZ.1009",
        "count": 89,
        "src": "http://d.duotuwang.com/2019/03/18/14618/0.jpg"
    },
    {
        "href": "http://d.duotuwang.com/2019/03/17/14500/",
        "name": "[ROSI\u5199\u771f]\u53e3\u7f69\u7cfb\u5217 KZ.1008",
        "count": 28,
        "src": "http://d.duotuwang.com/2019/03/17/14500/0.jpg"
    },
    {
        "href": "http://d.duotuwang.com/2019/03/16/14501/",
        "name": "[ROSI\u5199\u771f]\u53e3\u7f69\u7cfb\u5217 KZ.1007",
        "count": 63,
        "src": "http://d.duotuwang.com/2019/03/16/14501/0.jpg"
    },
    {
        "href": "http://d.duotuwang.com/2019/03/15/14502/",
        "name": "[ROSI\u5199\u771f]\u53e3\u7f69\u7cfb\u5217 KZ.1006",
        "count": 66,
        "src": "http://d.duotuwang.com/2019/03/15/14502/0.jpg"
    },
    {
        "href": "http://d.duotuwang.com/2019/03/14/14503/",
        "name": "[ROSI\u5199\u771f]\u53e3\u7f69\u7cfb\u5217 KZ.1005",
        "count": 28,
        "src": "http://d.duotuwang.com/2019/03/14/14503/0.jpg"
    },
    {
        "href": "http://d.duotuwang.com/2019/03/13/14504/",
        "name": "[ROSI\u5199\u771f]\u53e3\u7f69\u7cfb\u5217 KZ.1004",
        "count": 30,
        "src": "http://d.duotuwang.com/2019/03/13/14504/0.jpg"
    },
    {
        "href": "http://d.duotuwang.com/2019/03/12/14435/",
        "name": "[ROSI\u5199\u771f]\u53e3\u7f69\u7cfb\u5217 KZ.1003",
        "count": 76,
        "src": "http://d.duotuwang.com/2019/03/12/14435/0.jpg"
    },
    {
        "href": "http://d.duotuwang.com/2019/03/11/14436/",
        "name": "[ROSI\u5199\u771f]\u53e3\u7f69\u7cfb\u5217 KZ.1002",
        "count": 34,
        "src": "http://d.duotuwang.com/2019/03/11/14436/0.jpg"
    },
    {
        "href": "http://d.duotuwang.com/2019/03/10/14437/",
        "name": "[ROSI\u5199\u771f]\u53e3\u7f69\u7cfb\u5217 KZ.1001",
        "count": 71,
        "src": "http://d.duotuwang.com/2019/03/10/14437/0.jpg"
    },
    {
        "href": "http://d.duotuwang.com/2019/03/09/14438/",
        "name": "[ROSI\u5199\u771f]\u53e3\u7f69\u7cfb\u5217 KZ.1000",
        "count": 46,
        "src": "http://d.duotuwang.com/2019/03/09/14438/0.jpg"
    },
    {
        "href": "http://d.duotuwang.com/2019/03/08/14439/",
        "name": "[ROSI\u5199\u771f]\u53e3\u7f69\u7cfb\u5217 KZ.999",
        "count": 84,
        "src": "http://d.duotuwang.com/2019/03/08/14439/0.jpg"
    },
    {
        "href": "http://d.duotuwang.com/2019/03/07/14440/",
        "name": "[ROSI\u5199\u771f]\u53e3\u7f69\u7cfb\u5217 KZ.998",
        "count": 31,
        "src": "http://d.duotuwang.com/2019/03/07/14440/0.jpg"
    },
    {
        "href": "http://d.duotuwang.com/2019/03/06/14441/",
        "name": "[ROSI\u5199\u771f]\u53e3\u7f69\u7cfb\u5217 KZ.997",
        "count": 36,
        "src": "http://d.duotuwang.com/2019/03/06/14441/0.jpg"
    },
    {
        "href": "http://d.duotuwang.com/2019/03/05/14442/",
        "name": "[ROSI\u5199\u771f]\u53e3\u7f69\u7cfb\u5217 KZ.996",
        "count": 72,
        "src": "http://d.duotuwang.com/2019/03/05/14442/0.jpg"
    },
    {
        "href": "http://d.duotuwang.com/2019/03/04/14443/",
        "name": "[ROSI\u5199\u771f]\u53e3\u7f69\u7cfb\u5217 KZ.995",
        "count": 53,
        "src": "http://d.duotuwang.com/2019/03/04/14443/0.jpg"
    },
    {
        "href": "http://d.duotuwang.com/2019/03/03/14444/",
        "name": "[ROSI\u5199\u771f]\u53e3\u7f69\u7cfb\u5217 KZ.994",
        "count": 68,
        "src": "http://d.duotuwang.com/2019/03/03/14444/0.jpg"
    },
    {
        "href": "http://d.duotuwang.com/2019/03/02/14445/",
        "name": "[ROSI\u5199\u771f]\u53e3\u7f69\u7cfb\u5217 KZ.993",
        "count": 42,
        "src": "http://d.duotuwang.com/2019/03/02/14445/0.jpg"
    },
    {
        "href": "http://d.duotuwang.com/2019/03/01/14499/",
        "name": "[ROSI\u5199\u771f]\u53e3\u7f69\u7cfb\u5217 KZ.992",
        "count": 44,
        "src": "http://d.duotuwang.com/2019/03/01/14499/0.jpg"
    },
    {
        "href": "http://d.duotuwang.com/2019/02/28/14424/",
        "name": "[ROSI\u5199\u771f]\u53e3\u7f69\u7cfb\u5217 KZ.991",
        "count": 60,
        "src": "http://d.duotuwang.com/2019/02/28/14424/0.jpg"
    },
    {
        "href": "http://d.duotuwang.com/2019/02/27/14425/",
        "name": "[ROSI\u5199\u771f]\u53e3\u7f69\u7cfb\u5217 KZ.990",
        "count": 37,
        "src": "http://d.duotuwang.com/2019/02/27/14425/0.jpg"
    }
]